{
  "common": {
    "loading": "Loading Peace...",
    "back": "Back",
    "close": "Close",
    "play_sudoku": "Play Sudoku",
    "start_puzzle": "Start Puzzle"
  },
  "nav": {
    "logo": "PlayForCalm",
    "sudoku": "Sudoku",
    "puzzle": "Puzzle",
    "home": "Home"
  },
  "gamification": {
    "streak": "Focus Streak",
    "level": "Novice Calm",
    "xp": "XP",
    "daily_goal": "Daily Quest",
    "progress_text": "Complete 1 more game for daily bonus!",
    "complete": "Completed"
  },
  "home": {
    "greeting_morning": "Good Morning,",
    "greeting_afternoon": "Good Afternoon,",
    "greeting_evening": "Good Evening,",
    "hero_title": "Ready to Train",
    "hero_highlight": "Your Focus?",
    "subtitle": "Simple games to train your brain and calm your mind. No scores, no pressure.",
    "card_play": "PLAY NOW",
    "hero_button": "Start Exploring",
    "card_sudoku_title": "Sudoku Zen",
    "card_sudoku_desc": "Arrange numbers, declutter your mind with logic.",
    "card_puzzle_title": "Memory Lane",
    "card_puzzle_desc": "Visualize and piece together your fond memories.",
    "benefits_title": "The Journey to Serenity",
    "benefit_1_title": "Digital Detox",
    "benefit_1_desc": "Detach yourself from notifications and social media noise for a while.",
    "benefit_2_title": "Deep Focus",
    "benefit_2_desc": "Train your brain to remain calm while completing a single, simple task.",
    "benefit_3_title": "Clear Mind",
    "benefit_3_desc": "Achieve a 'Flow' state where anxiety is replaced by inner satisfaction.",
    "quote_text": "Calmness is not the absence of trouble, but the ability to deal with it with a clear head.",
    "quote_title": "Today's Philosophy",
    "step_o" : "Step",
    "description": "Choose the activity that best suits your",
    "rhythm": "mental rhythm",
    "current": "right now."
  },
  "sudoku": {
    "difficulty_label": "Difficulty",
    "mistakes_label": "Mistakes",
    "time_label": "Time",
    "difficulty_select": "Select Mode",
    "easy": "Easy",
    "medium": "Medium",
    "hard": "Hard",
    "timer": "Time",
    "mistakes": "Mistakes",
    "notes": "Notes",
    "new_game": "New Game",
    "pause": "Pause",
    "resume": "Resume",
    "paused_status": "PAUSED",
    "paused_title": "Paused",
    "paused_desc": "Take a deep breath...",
    "resume_btn": "Resume Focus",
    "won_title": "Serenity Achieved! ✨",
    "won_desc": "Great job! You've trained your focus today.",
    "play_again": "Play Again",
    "game_over": "Game Over",
    "too_many_mistakes": "Too many mistakes.",
    "try_again": "Try Again"
  },
  
"puzzle": {
    "title": "Puzzle",
    "desc": "Piece together scattered fragments into a whole memory.",
    "upload_label": "Choose Photo",
    "change_photo": "Change Photo",
    "pieces_count": "Pieces",
    "time": "Time",
    "difficulty": "Piece Count",
    "start_game": "Start Puzzle",
    "won_title": "Perfect! 🧩",
    "won_desc": "Every piece has found its place.",
    "select_image": "Choose Photo",
    "pieces": "Pieces",
    "time_taken": "Play Time",
    "play_again": "Play Again",
    "back_to_menu": "Switch Image / Level"
  },

  "footer": {
    "text": "Built for focus, not addiction."
  },
  "jigsaw": {
    "upload": "Upload"
  }
}